{"IFS.fairspec.version":"0.0.1-alpha-2021_06_27",
"IFS.fairspec.data.license.uri":"https://creativecommons.org/licenses/by-nc/4.0/",
"IFS.fairspec.data.license.name":"cc-by-nc-4.0",
"IFS.extractor.version":"0.0.1-alpha_2021_06_21",
"IFS.extractor.code":"https://github.com/BobHanson/IUPAC-FAIRSpec/blob/main/src/main/java/com/integratedgraphics/ifs/Extractor.java",
"IFS.extractor.list.type":"ignored",
"IFS.extractor.scirpt":"_IFS_extract.json",
"IFS.extractor.source":"https://ndownloader.figshare.com/files/22567817",
"IFS.extractor.creation.date":"29 Jun 2021 15:24:30 GMT",
"IFS.extractor.count":62,
"IFS.extractor.list":
[
"1.zip|1_13C/desktop.ini"
,"1.zip|1_13C/pdata/1/desktop.ini"
,"1.zip|1_13C/pdata/desktop.ini"
,"1.zip|1_1H/desktop.ini"
,"1.zip|1_1H/pdata/1/desktop.ini"
,"1.zip|1_1H/pdata/desktop.ini"
,"1.zip|desktop.ini"
,"10.zip|10_13C/desktop.ini"
,"10.zip|10_13C/pdata/1/desktop.ini"
,"10.zip|10_13C/pdata/desktop.ini"
,"10.zip|10_1H/desktop.ini"
,"10.zip|10_1H/pdata/1/desktop.ini"
,"10.zip|10_1H/pdata/desktop.ini"
,"10.zip|desktop.ini"
,"11.zip|11_13C/desktop.ini"
,"11.zip|11_13C/pdata/1/desktop.ini"
,"11.zip|11_13C/pdata/desktop.ini"
,"11.zip|11_1H/desktop.ini"
,"11.zip|11_1H/pdata/1/desktop.ini"
,"11.zip|11_1H/pdata/desktop.ini"
,"11.zip|desktop.ini"
,"13.zip|13_13C/desktop.ini"
,"13.zip|13_1H/desktop.ini"
,"13.zip|desktop.ini"
,"16.zip|16_13C/desktop.ini"
,"16.zip|16_13C/pdata/1/desktop.ini"
,"16.zip|16_13C/pdata/desktop.ini"
,"16.zip|16_1H/desktop.ini"
,"16.zip|16_1H/pdata/1/desktop.ini"
,"16.zip|16_1H/pdata/desktop.ini"
,"16.zip|desktop.ini"
,"16.zip|dia-16_13C/desktop.ini"
,"16.zip|dia-16_13C/pdata/1/desktop.ini"
,"16.zip|dia-16_13C/pdata/desktop.ini"
,"16.zip|dia-16_1H/desktop.ini"
,"16.zip|dia-16_1H/pdata/1/desktop.ini"
,"16.zip|dia-16_1H/pdata/desktop.ini"
,"17.zip|17_13C/desktop.ini"
,"17.zip|17_13C/pdata/1/desktop.ini"
,"17.zip|17_1H/desktop.ini"
,"17.zip|17_1H/pdata/1/desktop.ini"
,"17.zip|desktop.ini"
,"21.zip|21_13C/desktop.ini"
,"21.zip|21_13C/pdata/desktop.ini"
,"21.zip|21_1H/desktop.ini"
,"21.zip|21_1H/pdata/1/desktop.ini"
,"21.zip|21_1H/pdata/desktop.ini"
,"21.zip|desktop.ini"
,"8.zip|8_13C/desktop.ini"
,"8.zip|8_1H/desktop.ini"
,"8.zip|8_1H/pdata/1/desktop.ini"
,"8.zip|8_1H/pdata/desktop.ini"
,"8.zip|desktop.ini"
,"9.zip|9_13C/desktop.ini"
,"9.zip|9_13C/pdata/1/desktop.ini"
,"9.zip|9_13C/pdata/desktop.ini"
,"9.zip|9_1H/desktop.ini"
,"9.zip|9_1H/pdata/1/desktop.ini"
,"9.zip|9_1H/pdata/desktop.ini"
,"9.zip|desktop.ini"
,"desktop.ini"
,"desktop.ini"
]}
